bunruija/__init__.py
bunruija/classifiers/__init__.py
bunruija/classifiers/classifier.py
bunruija/classifiers/lstm.py
bunruija/classifiers/prado/__init__.py
bunruija/classifiers/prado/model.py
bunruija/classifiers/qrnn/__init__.py
bunruija/classifiers/qrnn/model.py
bunruija/classifiers/qrnn/qrnn_layer.py
bunruija/classifiers/transformer.py
bunruija/data/__init__.py
bunruija/data/dataset.py
bunruija/data/dictionary.py
bunruija/dataclass.py
bunruija/evaluate.py
bunruija/evaluator.py
bunruija/feature_extraction/__init__.py
bunruija/feature_extraction/sentence_pair.py
bunruija/feature_extraction/sequence.py
bunruija/filters/__init__.py
bunruija/filters/filter.py
bunruija/filters/pos_filter.py
bunruija/gen_yaml.py
bunruija/modules/__init__.py
bunruija/modules/static_embedding.py
bunruija/modules/vector_processor.pyx
bunruija/options.py
bunruija/pipeline_builder.py
bunruija/predict.py
bunruija/predictor.py
bunruija/saver.py
bunruija/tokenizers/__init__.py
bunruija/tokenizers/mecab_tokenizer.py
bunruija/tokenizers/space_tokenizer.py
bunruija/tokenizers/tokenizer.py
bunruija/train.py
bunruija/trainer.py
bunruija/modules/vector_processor.cpp
bunruija/modules/vector_processor.cpython-310-darwin.so
bunruija-0.2.0.dist-info/METADATA
bunruija-0.2.0.dist-info/WHEEL
bunruija-0.2.0.dist-info/entry_points.txt
bunruija-0.2.0.dist-info/RECORD
