Metadata-Version: 2.1
Name: bunruija
Version: 0.2.0
Summary: A text classification toolkit
Home-page: https://github.com/tma15
Author: Takuya Makino
Author-email: takuyamakino15@gmail.com
Requires-Python: >=3.10,<3.11
Classifier: Programming Language :: Python :: 3
Classifier: Programming Language :: Python :: 3.10
Requires-Dist: Cython (>=3.0.8,<4.0.0)
Requires-Dist: datasets (>=2.16.0,<3.0.0)
Requires-Dist: fugashi (>=1.1.1,<2.0.0)
Requires-Dist: hydra-core (>=1.2.0,<2.0.0)
Requires-Dist: ipadic (>=1.0.0,<2.0.0)
Requires-Dist: lightgbm (>=4.2.0,<5.0.0)
Requires-Dist: loguru (>=0.7.2,<0.8.0)
Requires-Dist: mmh3 (>=3.0.0,<4.0.0)
Requires-Dist: ruamel-yaml (>=0.18.5,<0.19.0)
Requires-Dist: scikit-learn (>=1.0.2,<2.0.0)
Requires-Dist: scipy (>=1.8.0,<2.0.0)
Requires-Dist: torch (>=2.1.2,<3.0.0)
Requires-Dist: transformers (>=4.38.1,<5.0.0)
Requires-Dist: unidic-lite (>=1.0.8,<2.0.0)
Project-URL: Repository, https://github.com/tma15/bunruija
